lspsp/__init__.py
lspsp/executable.py
lspsp/lspmon.py
lspsp/lspnotify.py
lspsp/lspsp.py
lspsp/mailbuilder.py
lspsp/main.py
lspsp/monexec.py
lspsp/resource/mail.html
lspsp/resource/test.html
lspsp-1.0.4.data/data/etc/lspsp/config.json.template
lspsp-1.0.4.dist-info/METADATA
lspsp-1.0.4.dist-info/WHEEL
lspsp-1.0.4.dist-info/entry_points.txt
lspsp-1.0.4.dist-info/top_level.txt
lspsp-1.0.4.dist-info/RECORD
